LICENSE
MANIFEST.in
README.rst
setup.py
kigo/__init__.py
kigo/etl/__init__.py
kigo/etl/configuration.py
kigo/etl/extractors/__init__.py
kigo/etl/extractors/fabric.py
kigo/etl/extractors/operators.py
kigo/etl/extractors/slicers.py
kigo/etl/file/__init__.py
kigo/etl/file/loader.py
kigo/etl/file/readers.py
kigo/etl/mapper/__init__.py
kigo/etl/mapper/archetype.py
kigo/etl/mapper/keys.py
kigo/etl/mapper/mapping.py
kigo/etl/mapper/typeof.py
kigo/etl/runtime/__init__.py
kigo/etl/runtime/registry.py
kigo/etl/runtime/runtime.py
kigo/etl/storage/__init__.py
kigo/etl/storage/memdb.py
kigo/etl/unittest/__init__.py
kigo/etl/unittest/decorators.py
kigo/test/__init__.py
kigo/test/etl/__init__.py
kigo/test/etl/engine/__init__.py
kigo/test/etl/unittest/__init__.py
kigo/test/etl/unittest/concatenate_test.py
kigo/test/etl/unittest/decorators_test.py
kigo/test/etl/unittest/resources/__init__.py
kigo/test/etl/unittest/resources/entities.py
kigo/test/etl/unittest/resources/entity_1.py
kigo_etl.egg-info/PKG-INFO
kigo_etl.egg-info/SOURCES.txt
kigo_etl.egg-info/dependency_links.txt
kigo_etl.egg-info/requires.txt
kigo_etl.egg-info/top_level.txt
test/__init__.py