Metadata-Version: 2.1
Name: kigo-etl
Version: 0.0.9
Summary: Python ETL framework
Home-page: https://github.com/AsyncMicroStack/kigo-etl
Author: Kigo
Author-email: kigo@architekt-it.pl
License: UNKNOWN
Platform: UNKNOWN
Classifier: Development Status :: 1 - Planning
Classifier: Programming Language :: Python :: 3.8
Classifier: License :: OSI Approved :: Apache Software License
Classifier: Operating System :: OS Independent
Requires-Python: >=3.8
Provides-Extra: docs
License-File: LICENSE
